coauction/__init__.py
coauction-0.2.dist-info/LICENSE
coauction-0.2.dist-info/METADATA
coauction-0.2.dist-info/WHEEL
coauction-0.2.dist-info/top_level.txt
coauction-0.2.dist-info/RECORD
