Metadata-Version: 2.1
Name: coauction
Version: 0.2
Summary: This repository will contain the source codes for newly proposed auction systems in our proposed economics research paper. Targeted to update the repository before : 15th March 2019
Home-page: https://github.com/mr-ravin/collaborative-auction
Author: Ravin Kumar
Author-email: mr.ravin_kumar@hotmail.com
License: UNKNOWN
Platform: UNKNOWN
Classifier: Programming Language :: Python :: 3
Classifier: License :: OSI Approved :: GNU General Public License (GPL)
Classifier: Operating System :: OS Independent
